{"name":"get-repo-package-json","version":"1.0.2","description":"Fetch a GitHub repository's package.json file using the GitHub API","main":"index.js","scripts":{"test":"mocha && standard"},"repository":"https://github.com/zeke/get-repo-package-json","keywords":["package.json","github","api","repository","metadata","npm"],"license":"MIT","devDependencies":{"chai":"^3.5.0","mocha":"^3.0.1","nock":"^8.0.0","require-dir":"^0.3.0","standard":"^7.1.2"},"dependencies":{"github-url-to-object":"^2.2.3","got":"^6.3.0"},"standard":{"env":{"mocha":true}},"gitHead":"e6284dcd2d88ed28c1a9b974ea44804de9a3b39e","homepage":"https://github.com/zeke/get-repo-package-json#readme","versions":[{"number":"1.0.0","date":"2016-08-07T04:50:39.172Z"},{"number":"1.0.1","date":"2016-11-19T05:20:30.840Z"},{"number":"1.0.2","date":"2016-11-19T05:24:47.157Z"}],"readme":"# get-repo-package-json\n\nFetch a GitHub repository's package.json file using the GitHub API\n\n## Installation\n\n```sh\nnpm install get-repo-package-json --save\n```\n\n## Usage\n\nThe basics:\n\n```js\nconst getPackage = require('get-repo-package-json')\n\ngetPackage('segmentio/nightmare', function (err, pkg) {\n  if (err) throw err\n  // pkg is a JSON object\n})\n```\n\nTo fetch a specific commit/branch/tag, use a long-form URL:\n\n```js\ngetPackage('https://github.com/monkey/business/tree/experiment', function (err, pkg) {\n  if (err) throw err\n  // pkg is a JSON object\n})\n```\n\nOr specify a `ref` option:\n\n```js\ngetPackage('monkey/business', {ref: '0e783153885ed78f71d138085a77644ff8e59aa1'}, function (err, pkg) {\n  if (err) throw err\n  // pkg is a JSON object\n})\n```\n\nTo see more supported repository string formats, see the\n[github-url-to-object](https://zeke.github.io/github-url-to-object/) demo.\n\n## API\n\nThis package exports a single function:\n\n### `getPackage(repository, [options], callback)`\n\n- `repository` (string) - Any string supported by\n[github-url-to-object](https://zeke.github.io/github-url-to-object/).\n- `options` (optional object)\n  - `access_token` - GitHub API key. Can also be set as a `GITHUB_ACCESS_TOKEN` environment variable.\n  - `ref` - The name of the commit/branch/tag. Defaults to nothing, so the GitHub API will return the repo's default branch.\n- `callback(err, pkg)` (function) - node-style error-first callback\n\n## Tests\n\n```sh\nnpm install\nnpm test\n```\n\n## Dependencies\n\n- [github-url-to-object](https://github.com/zeke/github-url-to-object): Extract user, repo, and other interesting properties from GitHub URLs\n- [got](https://github.com/sindresorhus/got): Simplified HTTP requests\n\n## Dev Dependencies\n\n- [chai](https://github.com/chaijs/chai): BDD/TDD assertion library for node.js and the browser. Test framework agnostic.\n- [mocha](https://github.com/mochajs/mocha): simple, flexible, fun test framework\n- [nock](https://github.com/node-nock/nock): HTTP Server mocking for Node.js\n- [require-dir](https://github.com/aseemk/requireDir): Helper to require() directories.\n- [standard](https://github.com/feross/standard): JavaScript Standard Style\n\n\n## License\n\nMIT\n\n_Generated by [package-json-to-readme](https://github.com/zeke/package-json-to-readme)_\n","created":"2016-08-07T04:50:39.172Z","modified":"2016-11-19T05:24:47.157Z","lastPublisher":{"name":"zeke","email":"zeke@sikelianos.com"},"owners":[{"name":"zeke","email":"zeke@sikelianos.com"}],"other":{"_attachments":{},"_from":".","_id":"get-repo-package-json","_nodeVersion":"7.0.0","_npmOperationalInternal":{"host":"packages-12-west.internal.npmjs.com","tmp":"tmp/get-repo-package-json-1.0.2.tgz_1479533086887_0.04926127870567143"},"_npmUser":{"name":"zeke","email":"zeke@sikelianos.com"},"_npmVersion":"3.10.8","_rev":"3-22b6767dec633401852331740f7e5c3b","_shasum":"b8ce50068049ac96e87f7c8c8e2eccc012f7fd00","author":{"name":"Zeke Sikelianos","email":"zeke@sikelianos.com","url":"http://zeke.sikelianos.com"},"bugs":{"url":"https://github.com/zeke/get-repo-package-json/issues"},"directories":{},"dist-tags":{"latest":"1.0.2"},"dist":{"shasum":"b8ce50068049ac96e87f7c8c8e2eccc012f7fd00","tarball":"http://registry.npmjs.org/get-repo-package-json/-/get-repo-package-json-1.0.2.tgz"},"maintainers":[{"name":"zeke","email":"zeke@sikelianos.com"}],"readmeFilename":"readme.md","time":{"modified":"2016-11-19T05:24:47.157Z","created":"2016-08-07T04:50:39.172Z","1.0.0":"2016-08-07T04:50:39.172Z","1.0.1":"2016-11-19T05:20:30.840Z","1.0.2":"2016-11-19T05:24:47.157Z"}}}