{"name":"github-api","version":"3.0.0","license":"BSD-3-Clause-Clear","description":"A higher-level wrapper around the Github API.","main":"dist/components/GitHub.js","scripts":{"clean":"gulp clean","build":"gulp build","test":"mocha --opts ./mocha.opts test/*.spec.js","test-coverage":"NODE_ENV=test nyc mocha --opts ./mocha.opts test/*.spec.js","test-verbose":"DEBUG=github* npm test","lint":"gulp lint","make-docs":"jsdoc -c .jsdoc.json --verbose","release":"./release.sh","codecov":"nyc report --reporter=text-lcov > coverage.lcov && codecov"},"babel":{"presets":["es2015"],"plugins":[["add-module-exports","transform-es2015-modules-umd"]],"env":{"development":{"sourceMaps":"inline"},"test":{"plugins":["istanbul"]}}},"nyc":{"sourceMap":false,"instrument":false},"files":["dist/*"],"dependencies":{"axios":"^0.15.2","debug":"^2.2.0","js-base64":"^2.1.9","utf8":"^2.1.1"},"devDependencies":{"babel-core":"^6.7.7","babel-plugin-add-module-exports":"^0.2.1","babel-plugin-istanbul":"3.0.0","babel-plugin-transform-es2015-modules-umd":"^6.5.0","babel-preset-es2015":"^6.5.0","babel-register":"^6.7.2","babelify":"^7.3.0","browserify":"^13.0.0","codecov":"^1.0.1","del":"^2.2.0","eslint-config-google":"^0.7.0","eslint-plugin-mocha":"^4.7.0","gulp":"^3.9.0","gulp-babel":"^6.1.2","gulp-eslint":"^3.0.1","gulp-jscs":"^4.0.0","gulp-jscs-stylish":"^1.3.0","gulp-rename":"^1.2.2","gulp-sourcemaps":"^2.2.0","gulp-uglify":"^2.0.0","jsdoc":"^3.4.0","minami":"^1.1.1","mocha":"^3.1.2","must":"^0.13.1","nock":"^9.0.2","nyc":"9.0.1","vinyl-buffer":"^1.0.0","vinyl-source-stream":"^1.1.0"},"repository":"https://github.com/github-tools/github","keywords":["github","api"],"gitHead":"f075749ed4234c7d76f122879523fbca2eb01f86","homepage":"https://github.com/github-tools/github#readme","versions":[{"number":"0.7.0","date":"2013-07-06T20:25:33.054Z"},{"number":"0.10.1","date":"2014-12-12T19:39:13.897Z"},{"number":"0.10.2","date":"2014-12-22T15:26:43.896Z"},{"number":"0.10.3","date":"2014-12-22T15:32:25.988Z"},{"number":"0.10.4","date":"2015-03-20T17:01:59.830Z"},{"number":"0.10.6","date":"2015-05-26T07:11:39.813Z"},{"number":"0.10.7","date":"2015-11-13T16:57:28.325Z"},{"number":"0.11.2","date":"2016-01-25T14:34:52.209Z"},{"number":"1.0.0","date":"2016-04-27T21:29:52.854Z"},{"number":"1.1.0","date":"2016-05-03T14:16:21.622Z"},{"number":"1.2.0","date":"2016-05-11T21:47:39.199Z"},{"number":"1.2.1","date":"2016-05-12T12:36:43.485Z"},{"number":"1.3.0","date":"2016-05-17T16:17:16.108Z"},{"number":"2.0.0","date":"2016-05-19T18:51:29.914Z"},{"number":"2.1.0","date":"2016-05-25T22:25:46.988Z"},{"number":"2.2.0","date":"2016-05-27T19:48:13.670Z"},{"number":"2.3.0","date":"2016-06-17T14:45:15.182Z"},{"number":"2.4.0","date":"2016-09-16T15:24:48.053Z"},{"number":"3.0.0","date":"2017-01-04T14:59:36.777Z"}],"readme":"# Github.js\n\n[![Downloads per month](https://img.shields.io/npm/dm/github-api.svg?maxAge=2592000)][npm-package]\n[![Latest version](https://img.shields.io/npm/v/github-api.svg?maxAge=3600)][npm-package]\n[![Gitter](https://img.shields.io/gitter/room/github-tools/github.js.svg?maxAge=2592000)][gitter]\n[![Travis](https://img.shields.io/travis/github-tools/github.svg?maxAge=60)][travis-ci]\n[![Codecov](https://img.shields.io/codecov/c/github/github-tools/github.svg?maxAge=2592000)][codecov]\n\nGithub.js provides a minimal higher-level wrapper around Github's API.\n\n## Usage\n\n```javascript\n/*\n   Data can be retrieved from the API either using callbacks (as in versions < 1.0)\n   or using a new promise-based API. The promise-based API returns the raw Axios\n   request promise.\n */\nimport GitHub from 'github-api';\n\n// unauthenticated client\nconst gh = new GitHub();\nlet gist = gh.getGist(); // not a gist yet\ngist.create({\n   public: true,\n   description: 'My first gist',\n   files: {\n      \"file1.txt\": {\n         content: \"Aren't gists great!\"\n      }\n   }\n}).then(function({data}) {\n   // Promises!\n   let createdGist = data;\n   return gist.read();\n}).then(function({data}) {\n   let retrievedGist = data;\n   // do interesting things\n});\n```\n\n```javascript\nvar GitHub = require('github-api');\n\n// basic auth\nvar gh = new GitHub({\n   username: 'FOO',\n   password: 'NotFoo'\n   /* also acceptable:\n      token: 'MY_OAUTH_TOKEN'\n    */\n});\n\nvar me = gh.getUser(); // no user specified defaults to the user for whom credentials were provided\nme.listNotifications(function(err, notifications) {\n   // do some stuff\n});\n\nvar clayreimann = gh.getUser('clayreimann');\nclayreimann.listStarredRepos(function(err, repos) {\n   // look at all the starred repos!\n});\n```\n\n## API Documentation\n\n[API documentation][docs] is hosted on github pages, and is generated from JSDoc; any contributions\nshould include updated JSDoc.\n\n## Installation\nGithub.js is available from `npm` or [unpkg][unpkg].\n\n```shell\nnpm install github-api\n```\n\n```html\n<!-- just github-api source (5.3kb) -->\n<script src=\"https://unpkg.com/github-api/dist/GitHub.min.js\"></script>\n\n<!-- standalone (20.3kb) -->\n<script src=\"https://unpkg.com/github-api/dist/GitHub.bundle.min.js\"></script>\n```\n\n## Compatibility\n`Github.js` is tested on Node.js:\n* 6.x\n\nNote: `Github.js` uses Promise, hence it will not work in Node.js < 4 without polyfill.\n\n[codecov]: https://codecov.io/github/github-tools/github?branch=master\n[docs]: http://github-tools.github.io/github/\n[gitter]: https://gitter.im/github-tools/github\n[npm-package]: https://www.npmjs.com/package/github-api/\n[unpkg]: https://unpkg.com/github-api/\n[travis-ci]: https://travis-ci.org/github-tools/github\n","starsCount":15,"created":"2013-07-06T20:25:31.605Z","modified":"2017-05-01T17:57:05.889Z","lastPublisher":{"name":"clayreimann","email":"clayreimann@gmail.com"},"owners":[{"name":"aendrew","email":"aendrew@aendrew.com"},{"name":"aurelioderosa","email":"a.derosa@audero.it"},{"name":"clayreimann","email":"clayreimann@gmail.com"},{"name":"ingalls","email":"nicholas.ingalls@gmail.com"},{"name":"michael","email":"michael@substance.io"}],"other":{"_attachments":{},"_from":".","_id":"github-api","_nodeVersion":"5.12.0","_npmOperationalInternal":{"host":"packages-18-east.internal.npmjs.com","tmp":"tmp/github-api-3.0.0.tgz_1483541976152_0.4974204604513943"},"_npmUser":{"name":"clayreimann","email":"clayreimann@gmail.com"},"_npmVersion":"4.0.5","_rev":"9-9364bd4f53cf3049aa2503818a33c372","_shasum":"2832f98d0d3a83f1485e2db32c9259e4b9c40a75","bugs":{"url":"https://github.com/github-tools/github/issues"},"contributors":[{"name":"Ændrew Rininsland","email":"aendrew.rininsland@thetimes.co.uk","url":"http://www.aendrew.com"},{"name":"Aurelio De Rosa","email":"a.derosa@audero.it","url":"http://www.audero.it/"},{"name":"Clay Reimann","email":"clayreimann@gmail.com","url":"http://clayreimann.me"},{"name":"Michael Aufreiter","url":"http://substance.io"},{"name":"Mathieu Dutour","email":"mathieu@dutour.me","url":"https://github.com/mathieudutour"}],"directories":{},"dist-tags":{"latest":"3.0.0"},"dist":{"shasum":"2832f98d0d3a83f1485e2db32c9259e4b9c40a75","tarball":"http://registry.npmjs.org/github-api/-/github-api-3.0.0.tgz"},"maintainers":[{"name":"aendrew","email":"aendrew@aendrew.com"},{"name":"aurelioderosa","email":"a.derosa@audero.it"},{"name":"clayreimann","email":"clayreimann@gmail.com"},{"name":"ingalls","email":"nicholas.ingalls@gmail.com"},{"name":"michael","email":"michael@substance.io"}],"readmeFilename":"README.md","time":{"modified":"2017-05-01T17:57:05.889Z","created":"2013-07-06T20:25:31.605Z","0.7.0":"2013-07-06T20:25:33.054Z","0.10.1":"2014-12-12T19:39:13.897Z","0.10.2":"2014-12-22T15:26:43.896Z","0.10.3":"2014-12-22T15:32:25.988Z","0.10.4":"2015-03-20T17:01:59.830Z","0.10.6":"2015-05-26T07:11:39.813Z","0.10.7":"2015-11-13T16:57:28.325Z","0.11.2":"2016-01-25T14:34:52.209Z","1.0.0":"2016-04-27T21:29:52.854Z","1.1.0":"2016-05-03T14:16:21.622Z","1.2.0":"2016-05-11T21:47:39.199Z","1.2.1":"2016-05-12T12:36:43.485Z","1.3.0":"2016-05-17T16:17:16.108Z","2.0.0":"2016-05-19T18:51:29.914Z","2.1.0":"2016-05-25T22:25:46.988Z","2.2.0":"2016-05-27T19:48:13.670Z","2.3.0":"2016-06-17T14:45:15.182Z","2.4.0":"2016-09-16T15:24:48.053Z","3.0.0":"2017-01-04T14:59:36.777Z"},"users":{"brentonhouse":true,"tunnckocore":true,"tlee":true,"dongguangming":true,"arnoldstoba":true,"emarcs":true,"gormartsen":true,"danielbayley":true,"haxpor":true,"logol":true,"miloc":true,"tamer1an":true,"decoded":true,"shreyawhiz":true,"alshamiri2":true}}}