{"name":"github-api-base","version":"2.0.1","description":"Basic functionality required for all github api calls.","main":"index.js","scripts":{"lint":"jshint index.js","build":"babel --blacklist useStrict src/index.es6 -o index.js","test":"tape test/*","postbuild":"npm run lint","pretest":"npm run build"},"repository":"https://github.com/phoenixstormcrow/github-api-base","keywords":["github","api"],"license":"MIT","homepage":"https://github.com/phoenixstormcrow/github-api-base","devDependencies":{"babel":"^4.4.6","jshint":"^2.6.0","tape":"^3.5.0"},"gitHead":"68ae337feea520c8c8e75bcbd175c40ce518d924","versions":[{"number":"1.0.0","date":"2015-02-25T02:20:18.534Z"},{"number":"1.0.1","date":"2015-02-25T02:27:55.301Z"},{"number":"1.0.2","date":"2015-02-25T03:32:31.080Z"},{"number":"2.0.0","date":"2015-02-25T22:22:52.563Z"},{"number":"2.0.1","date":"2015-02-27T00:15:35.705Z"}],"readme":"# github-api-base\nNode module providing basic functionality required for all github api calls.\n\n## Installation\n\n`npm install github-api-base`\n\n## Usage\n\n```\n> var base = require('github-api-base')\n\n> base\n{ base: 'https://api.github.com',\n  version: 3,\n  headers:\n   { Accept: 'application/vnd.github.v3+json',\n     'User-Agent': 'node_v0.11.14_x64_linux' } }\n\n> base.toString() === base.base\ntrue\n> base + \"/users/phoenixstormcrow\"\n'https://api.github.com/users/phoenixstormcrow'\n```\n\nThe module exports an object with the fields shown above. `base.headers['User-Agent']` is writable, all other properties are not.\n\nThe default User-Agent header is constructed from\n\n```\n`node_${process.version}_${process.arch}_${process.platform}`\n```\n\nso your value may differ. (I think I saw this technique used somewhere while screwing around on the internet. Unsure to whom credit is due.)\n\n `.toString` is provided as a convenience for composing api urls.\n\n\n```\n> var base = require('github-api-base')\n> var request = require('request')\n> var user = 'phoenixstormcrow'\n> var opts = {\n... url: base + \"/users/\" + user,\n... headers: base.headers\n... }\n\n> request(opts, function (err, response, body) { console.log(response.statusCode); })\n200\n```\n\nFeedback is very welcome.\n","starsCount":0,"created":"2015-02-25T02:20:18.534Z","modified":"2015-02-27T00:15:35.705Z","lastPublisher":{"name":"phoenixstormcrow","email":"phoenixstormcrow@gmail.com"},"owners":[{"name":"phoenixstormcrow","email":"phoenixstormcrow@gmail.com"}],"other":{"_attachments":{},"_from":".","_id":"github-api-base","_nodeVersion":"0.11.12","_npmUser":{"name":"phoenixstormcrow","email":"phoenixstormcrow@gmail.com"},"_npmVersion":"2.5.1","_rev":"1-fe92e8e3f5a4d20ef1956c54ec785032","_shasum":"d569e4bc797a7b9d4b5c8e72dc83e7556fcdfb3f","author":{"name":"Phoenix Stormcrow","email":"phoenixstormcrow@gmail.com"},"bugs":{"url":"https://github.com/phoenixstormcrow/github-api-base/issues"},"directories":{},"dist-tags":{"latest":"2.0.1"},"dist":{"shasum":"d569e4bc797a7b9d4b5c8e72dc83e7556fcdfb3f","tarball":"http://registry.npmjs.org/github-api-base/-/github-api-base-2.0.1.tgz"},"maintainers":[{"name":"phoenixstormcrow","email":"phoenixstormcrow@gmail.com"}],"readmeFilename":"README.md","time":{"modified":"2015-02-27T00:15:35.705Z","created":"2015-02-25T02:20:18.534Z","1.0.0":"2015-02-25T02:20:18.534Z","1.0.1":"2015-02-25T02:27:55.301Z","1.0.2":"2015-02-25T03:32:31.080Z","2.0.0":"2015-02-25T22:22:52.563Z","2.0.1":"2015-02-27T00:15:35.705Z"},"users":{}}}