{"name":"gitter-github-client","version":"0.1.1","description":"Gitter GitHub client","main":"lib/client.js","scripts":{"test":"mocha --recursive test/ --timeout 10000"},"repository":"https://github.com/gitterHQ/gittercat","keywords":["Gitter","GitHub"],"license":"MIT","homepage":"https://github.com/gitterHQ/gittercat","dependencies":{"lodash":"^3.3.0","q":"^1.2.0","request":"^2.53.0","require-directory":"^2.1.0"},"devDependencies":{"mocha":"^2.1.0"},"gitHead":"21bd87b2ffd456ed0e48c60775503cda3ca7fc1f","versions":[{"number":"0.1.1","date":"2015-02-22T18:41:26.920Z"},{"number":"0.1.2","date":"2015-02-22T19:05:33.663Z"}],"readme":"ERROR: No README data found!","created":"2015-02-22T18:41:26.920Z","modified":"2015-02-22T19:06:01.782Z","lastPublisher":{"name":"suprememoocow","email":"andrewn@datatribe.net"},"owners":[{"name":"suprememoocow","email":"andrewn@datatribe.net"}],"other":{"_attachments":{},"_from":".","_id":"gitter-github-client","_npmUser":{"name":"suprememoocow","email":"andrewn@datatribe.net"},"_npmVersion":"1.4.28","_rev":"1-ba2f6556ca2318d71446bb33c0abd390","_shasum":"f6542b64d9d3bf497aaaa5ac84aaf1763e0e57cf","author":{"name":"Andrew Newdigate","email":"andrewn@datatribe.net","url":"http://about.me/andrewnewdigate"},"bugs":{"url":"https://github.com/gitterHQ/gittercat/issues"},"directories":{},"dist-tags":{"latest":"0.1.1"},"dist":{"shasum":"f6542b64d9d3bf497aaaa5ac84aaf1763e0e57cf","tarball":"http://registry.npmjs.org/gitter-github-client/-/gitter-github-client-0.1.1.tgz"},"maintainers":[{"name":"suprememoocow","email":"andrewn@datatribe.net"}],"readmeFilename":"","time":{"modified":"2015-02-22T19:06:01.782Z","created":"2015-02-22T18:41:26.920Z","0.1.1":"2015-02-22T18:41:26.920Z","0.1.2":"2015-02-22T19:05:33.663Z"}}}